stateless_mcp/__init__.py
stateless_mcp/app.py
stateless_mcp/auth.py
stateless_mcp/config.py
stateless_mcp/dispatcher.py
stateless_mcp/errors.py
stateless_mcp/logging.py
stateless_mcp/mcp_protocol.py
stateless_mcp/metrics.py
stateless_mcp/models.py
stateless_mcp/ratelimit.py
stateless_mcp/registry.py
stateless_mcp/rpc.py
stateless_mcp/streaming.py
stateless_mcp/tools/__init__.py
stateless_mcp/tools/example.py
stateless_mcp-1.1.2.dist-info/licenses/LICENSE
stateless_mcp-1.1.2.dist-info/METADATA
stateless_mcp-1.1.2.dist-info/WHEEL
stateless_mcp-1.1.2.dist-info/entry_points.txt
stateless_mcp-1.1.2.dist-info/top_level.txt
stateless_mcp-1.1.2.dist-info/RECORD
