Metadata-Version: 2.4
Name: stateless-mcp
Version: 1.1.2
Summary: A stateless MCP server with full Model Context Protocol support
Author-email: Atrix21 <aditya.singireddy.21@gmail.com>
License: MIT
Project-URL: Homepage, https://github.com/Atrix21/s-mcp
Project-URL: Repository, https://github.com/Atrix21/s-mcp
Project-URL: Issues, https://github.com/Atrix21/s-mcp/issues
Keywords: mcp,json-rpc,stateless,fastapi,streaming,autogen
Classifier: Development Status :: 4 - Beta
Classifier: Intended Audience :: Developers
Classifier: Topic :: Software Development :: Libraries :: Python Modules
Classifier: Programming Language :: Python :: 3
Classifier: Programming Language :: Python :: 3.9
Classifier: Programming Language :: Python :: 3.10
Classifier: Programming Language :: Python :: 3.11
Classifier: Programming Language :: Python :: 3.12
Requires-Python: >=3.9
License-File: LICENSE
Requires-Dist: fastapi>=0.104.0
Requires-Dist: uvicorn[standard]>=0.24.0
Requires-Dist: pydantic>=2.5.0
Requires-Dist: pydantic-settings>=2.1.0
Provides-Extra: dev
Requires-Dist: pytest>=7.4.0; extra == "dev"
Requires-Dist: pytest-asyncio>=0.21.0; extra == "dev"
Requires-Dist: httpx>=0.25.0; extra == "dev"
Requires-Dist: black>=23.11.0; extra == "dev"
Requires-Dist: ruff>=0.1.6; extra == "dev"
Requires-Dist: mypy>=1.7.0; extra == "dev"
Dynamic: license-file
